LICENSE
MANIFEST.in
README.rst
RELEASE-VERSION
setup.py
docs/getting-started.rst
docs/installation.rst
docs/overview.rst
docs/pcap-api.rst
docs/toc.rst
examples/pcap_info.py
examples/pcap_query.py
gitpy_versioning/.git
gitpy_versioning/.gitignore
gitpy_versioning/README.md
gitpy_versioning/__init__.py
gitpy_versioning/test_gitpy_versioning.py
steelscript/__init__.py
steelscript.wireshark.egg-info/PKG-INFO
steelscript.wireshark.egg-info/SOURCES.txt
steelscript.wireshark.egg-info/dependency_links.txt
steelscript.wireshark.egg-info/entry_points.txt
steelscript.wireshark.egg-info/namespace_packages.txt
steelscript.wireshark.egg-info/not-zip-safe
steelscript.wireshark.egg-info/requires.txt
steelscript.wireshark.egg-info/top_level.txt
steelscript/wireshark/__init__.py
steelscript/wireshark/appfwk/__init__.py
steelscript/wireshark/appfwk/admin.py
steelscript/wireshark/appfwk/models.py
steelscript/wireshark/appfwk/plugin.py
steelscript/wireshark/appfwk/datasources/__init__.py
steelscript/wireshark/appfwk/datasources/wireshark_source.py
steelscript/wireshark/appfwk/devices/__init__.py
steelscript/wireshark/appfwk/devices/wireshark_device.py
steelscript/wireshark/appfwk/libs/__init__.py
steelscript/wireshark/appfwk/reports/__init__.py
steelscript/wireshark/appfwk/reports/wireshark_report.py
steelscript/wireshark/core/__init__.py
steelscript/wireshark/core/exceptions.py
steelscript/wireshark/core/pcap.py